{
    "original_index": 3,
    "prediction": 0.00093,
    "predicted_class": "Normal",
    "prediction_confidence": 99.91,
    "feature_count": 965,
    "original_target": 0,
    "original_target_class": "Normal",
    "prediction_correct": true,
    "features": {
        "dl_bitrate_1": -0.73884,
        "ul_bitrate_1": 0.32155,
        "ul_total_bytes_non_incr_1": 0.41359,
        "dl_total_bytes_non_incr_1": -0.73021,
        "dl_bitrate_2": -0.4206,
        "ul_bitrate_2": -0.14456,
        "ul_total_bytes_non_incr_2": -0.10064,
        "dl_total_bytes_non_incr_2": -0.3829,
        "dl_bitrate_3": -0.70467,
        "ul_bitrate_3": -0.58049,
        "ul_total_bytes_non_incr_3": -0.55968,
        "dl_total_bytes_non_incr_3": -0.66324,
        "dl_bitrate_4": -0.02073,
        "ul_bitrate_4": -0.40213,
        "ul_total_bytes_non_incr_4": -0.39039,
        "dl_total_bytes_non_incr_4": 0.01016,
        "dl_bitrate_5": -0.72224,
        "ul_bitrate_5": 0.44911,
        "ul_total_bytes_non_incr_5": 0.53124,
        "dl_total_bytes_non_incr_5": -0.69665,
        "dl_bitrate_6": -0.72823,
        "ul_bitrate_6": 0.38871,
        "ul_total_bytes_non_incr_6": 0.42547,
        "dl_total_bytes_non_incr_6": -0.7074,
        "dl_bitrate_7": -0.77466,
        "ul_bitrate_7": 0.30523,
        "ul_total_bytes_non_incr_7": 0.3813,
        "dl_total_bytes_non_incr_7": -0.74638,
        "dl_bitrate_8": -0.81408,
        "ul_bitrate_8": 0.23329,
        "ul_total_bytes_non_incr_8": 0.31494,
        "dl_total_bytes_non_incr_8": -0.7857,
        "dl_bitrate_9": -0.32545,
        "ul_bitrate_9": -0.56299,
        "ul_total_bytes_non_incr_9": -0.54304,
        "dl_total_bytes_non_incr_9": -0.29841,
        "dl_bitrate_10": -0.69344,
        "ul_bitrate_10": -0.57178,
        "ul_total_bytes_non_incr_10": -0.55746,
        "dl_total_bytes_non_incr_10": -0.65753,
        "dl_bitrate_11": -0.07114,
        "ul_bitrate_11": 0.0957,
        "ul_total_bytes_non_incr_11": 0.14764,
        "dl_total_bytes_non_incr_11": -0.04672,
        "dl_bitrate_12": -0.73058,
        "ul_bitrate_12": 0.41072,
        "ul_total_bytes_non_incr_12": 0.47881,
        "dl_total_bytes_non_incr_12": -0.69703,
        "dl_bitrate_13": -0.74551,
        "ul_bitrate_13": 0.36452,
        "ul_total_bytes_non_incr_13": 0.43288,
        "dl_total_bytes_non_incr_13": -0.71732,
        "dl_bitrate_14": -0.78058,
        "ul_bitrate_14": 0.2853,
        "ul_total_bytes_non_incr_14": 0.36865,
        "dl_total_bytes_non_incr_14": -0.74872,
        "dl_bitrate_15": -0.40139,
        "ul_bitrate_15": -0.21987,
        "ul_total_bytes_non_incr_15": -0.16411,
        "dl_total_bytes_non_incr_15": -0.37413,
        "dl_bitrate_16": -0.70324,
        "ul_bitrate_16": -0.57223,
        "ul_total_bytes_non_incr_16": -0.55533,
        "dl_total_bytes_non_incr_16": -0.67043,
        "dl_bitrate_17": -0.04392,
        "ul_bitrate_17": -0.35745,
        "ul_total_bytes_non_incr_17": -0.34551,
        "dl_total_bytes_non_incr_17": -0.01643,
        "dl_bitrate_18": -0.73149,
        "ul_bitrate_18": 0.39409,
        "ul_total_bytes_non_incr_18": 0.44319,
        "dl_total_bytes_non_incr_18": -0.70035,
        "dl_bitrate_19": -0.68353,
        "ul_bitrate_19": 0.61933,
        "ul_total_bytes_non_incr_19": 0.63375,
        "dl_total_bytes_non_incr_19": -0.65208,
        "dl_bitrate_20": -0.68832,
        "ul_bitrate_20": 0.58224,
        "ul_total_bytes_non_incr_20": 0.61405,
        "dl_total_bytes_non_incr_20": -0.66023,
        "dl_bitrate_21": -0.41959,
        "ul_bitrate_21": -0.13505,
        "ul_total_bytes_non_incr_21": -0.06934,
        "dl_total_bytes_non_incr_21": -0.39061,
        "dl_bitrate_22": -0.70865,
        "ul_bitrate_22": -0.57225,
        "ul_total_bytes_non_incr_22": -0.55515,
        "dl_total_bytes_non_incr_22": -0.68138,
        "dl_bitrate_23": -0.02662,
        "ul_bitrate_23": -0.48268,
        "ul_total_bytes_non_incr_23": -0.47652,
        "dl_total_bytes_non_incr_23": -0.00237,
        "dl_bitrate_24": -0.73581,
        "ul_bitrate_24": 0.38502,
        "ul_total_bytes_non_incr_24": 0.45808,
        "dl_total_bytes_non_incr_24": -0.70489,
        "dl_bitrate_25": -0.77439,
        "ul_bitrate_25": 0.27061,
        "ul_total_bytes_non_incr_25": 0.34748,
        "dl_total_bytes_non_incr_25": -0.74698,
        "dl_bitrate_26": -0.77807,
        "ul_bitrate_26": 0.34145,
        "ul_total_bytes_non_incr_26": 0.40345,
        "dl_total_bytes_non_incr_26": -0.74622,
        "dl_bitrate_27": -0.75257,
        "ul_bitrate_27": 0.31885,
        "ul_total_bytes_non_incr_27": 0.40062,
        "dl_total_bytes_non_incr_27": -0.73337,
        "dl_bitrate_28": -0.39687,
        "ul_bitrate_28": -0.482,
        "ul_total_bytes_non_incr_28": -0.45886,
        "dl_total_bytes_non_incr_28": -0.35083,
        "dl_bitrate_29": -0.70358,
        "ul_bitrate_29": -0.57491,
        "ul_total_bytes_non_incr_29": -0.55698,
        "dl_total_bytes_non_incr_29": -0.67506,
        "dl_bitrate_30": -0.03285,
        "ul_bitrate_30": -0.11071,
        "ul_total_bytes_non_incr_30": -0.08352,
        "dl_total_bytes_non_incr_30": 0.00131,
        "dl_bitrate_31": -0.77792,
        "ul_bitrate_31": 0.36127,
        "ul_total_bytes_non_incr_31": 0.42647,
        "dl_total_bytes_non_incr_31": -0.75258,
        "dl_bitrate_32": -0.77722,
        "ul_bitrate_32": 0.29082,
        "ul_total_bytes_non_incr_32": 0.35227,
        "dl_total_bytes_non_incr_32": -0.74538,
        "dl_bitrate_33": -0.77237,
        "ul_bitrate_33": 0.31305,
        "ul_total_bytes_non_incr_33": 0.40584,
        "dl_total_bytes_non_incr_33": -0.74521,
        "dl_bitrate_34": -0.41158,
        "ul_bitrate_34": 0.07235,
        "ul_total_bytes_non_incr_34": 0.12424,
        "dl_total_bytes_non_incr_34": -0.39169,
        "dl_bitrate_35": -0.71127,
        "ul_bitrate_35": -0.57583,
        "ul_total_bytes_non_incr_35": -0.55611,
        "dl_total_bytes_non_incr_35": -0.6732,
        "dl_bitrate_36": -0.38515,
        "ul_bitrate_36": -0.55857,
        "ul_total_bytes_non_incr_36": -0.5457,
        "dl_total_bytes_non_incr_36": -0.42614,
        "dl_bitrate_37": -0.39363,
        "ul_bitrate_37": 0.23852,
        "ul_total_bytes_non_incr_37": 0.30233,
        "dl_total_bytes_non_incr_37": -0.30344,
        "dl_bitrate_38": -0.77986,
        "ul_bitrate_38": 0.33587,
        "ul_total_bytes_non_incr_38": 0.40804,
        "dl_total_bytes_non_incr_38": -0.74695,
        "dl_bitrate_39": -0.73263,
        "ul_bitrate_39": 0.40451,
        "ul_total_bytes_non_incr_39": 0.46969,
        "dl_total_bytes_non_incr_39": -0.70134,
        "dl_bitrate_40": -0.68965,
        "ul_bitrate_40": 0.56054,
        "ul_total_bytes_non_incr_40": 0.58334,
        "dl_total_bytes_non_incr_40": -0.66442,
        "dl_bitrate_41": -0.38686,
        "ul_bitrate_41": -0.502,
        "ul_total_bytes_non_incr_41": -0.46972,
        "dl_total_bytes_non_incr_41": -0.35814,
        "dl_bitrate_42": -0.70427,
        "ul_bitrate_42": -0.57376,
        "ul_total_bytes_non_incr_42": -0.55619,
        "dl_total_bytes_non_incr_42": -0.66766,
        "dl_bitrate_43": -0.06115,
        "ul_bitrate_43": -0.06154,
        "ul_total_bytes_non_incr_43": -0.01667,
        "dl_total_bytes_non_incr_43": -0.03438,
        "dl_bitrate_44": -0.77172,
        "ul_bitrate_44": 0.33253,
        "ul_total_bytes_non_incr_44": 0.41829,
        "dl_total_bytes_non_incr_44": -0.74005,
        "dl_bitrate_45": -0.74828,
        "ul_bitrate_45": 0.35294,
        "ul_total_bytes_non_incr_45": 0.41451,
        "dl_total_bytes_non_incr_45": -0.71665,
        "dl_bitrate_46": -0.75156,
        "ul_bitrate_46": 0.34173,
        "ul_total_bytes_non_incr_46": 0.43341,
        "dl_total_bytes_non_incr_46": -0.73521,
        "dl_bitrate_47": -0.40387,
        "ul_bitrate_47": -0.01831,
        "ul_total_bytes_non_incr_47": 0.01975,
        "dl_total_bytes_non_incr_47": -0.36264,
        "dl_bitrate_48": -0.70546,
        "ul_bitrate_48": -0.57922,
        "ul_total_bytes_non_incr_48": -0.56328,
        "dl_total_bytes_non_incr_48": -0.68171,
        "dl_bitrate_49": -0.03735,
        "ul_bitrate_49": -0.53234,
        "ul_total_bytes_non_incr_49": -0.54333,
        "dl_total_bytes_non_incr_49": -0.00959,
        "dl_bitrate_50": -0.73253,
        "ul_bitrate_50": 0.46705,
        "ul_total_bytes_non_incr_50": 0.54524,
        "dl_total_bytes_non_incr_50": -0.70351,
        "dl_bitrate_51": -0.78218,
        "ul_bitrate_51": 0.34663,
        "ul_total_bytes_non_incr_51": 0.43219,
        "dl_total_bytes_non_incr_51": -0.74979,
        "dl_bitrate_52": -0.74231,
        "ul_bitrate_52": 0.34032,
        "ul_total_bytes_non_incr_52": 0.41303,
        "dl_total_bytes_non_incr_52": -0.71187,
        "dl_bitrate_53": -0.76181,
        "ul_bitrate_53": 0.396,
        "ul_total_bytes_non_incr_53": 0.47372,
        "dl_total_bytes_non_incr_53": -0.72879,
        "dl_bitrate_54": -0.36741,
        "ul_bitrate_54": -0.58487,
        "ul_total_bytes_non_incr_54": -0.56834,
        "dl_total_bytes_non_incr_54": -0.34709,
        "dl_bitrate_55": -0.69947,
        "ul_bitrate_55": -0.57412,
        "ul_total_bytes_non_incr_55": -0.55721,
        "dl_total_bytes_non_incr_55": -0.67078,
        "dl_bitrate_56": -0.09192,
        "ul_bitrate_56": -0.02961,
        "ul_total_bytes_non_incr_56": 0.02967,
        "dl_total_bytes_non_incr_56": -0.06426,
        "dl_bitrate_57": -0.75178,
        "ul_bitrate_57": 0.36564,
        "ul_total_bytes_non_incr_57": 0.43545,
        "dl_total_bytes_non_incr_57": -0.72485,
        "dl_bitrate_58": -0.765,
        "ul_bitrate_58": 0.34538,
        "ul_total_bytes_non_incr_58": 0.42334,
        "dl_total_bytes_non_incr_58": -0.74303,
        "dl_bitrate_59": -0.69693,
        "ul_bitrate_59": 0.61175,
        "ul_total_bytes_non_incr_59": 0.61911,
        "dl_total_bytes_non_incr_59": -0.6739,
        "dl_bitrate_60": -0.35894,
        "ul_bitrate_60": -0.22681,
        "ul_total_bytes_non_incr_60": -0.20256,
        "dl_total_bytes_non_incr_60": -0.32434,
        "dl_bitrate_61": -0.69595,
        "ul_bitrate_61": -0.58498,
        "ul_total_bytes_non_incr_61": -0.56445,
        "dl_total_bytes_non_incr_61": -0.66769,
        "dl_bitrate_62": -0.05773,
        "ul_bitrate_62": -0.34711,
        "ul_total_bytes_non_incr_62": -0.32453,
        "dl_total_bytes_non_incr_62": -0.02185,
        "dl_bitrate_63": -0.7767,
        "ul_bitrate_63": 0.38495,
        "ul_total_bytes_non_incr_63": 0.46499,
        "dl_total_bytes_non_incr_63": -0.74677,
        "dl_bitrate_64": -0.74577,
        "ul_bitrate_64": 0.33958,
        "ul_total_bytes_non_incr_64": 0.41277,
        "dl_total_bytes_non_incr_64": -0.71209,
        "dl_bitrate_65": -0.73162,
        "ul_bitrate_65": 0.41565,
        "ul_total_bytes_non_incr_65": 0.49182,
        "dl_total_bytes_non_incr_65": -0.71752,
        "dl_bitrate_66": -0.41849,
        "ul_bitrate_66": 0.19772,
        "ul_total_bytes_non_incr_66": 0.2421,
        "dl_total_bytes_non_incr_66": -0.37644,
        "dl_bitrate_67": -0.70974,
        "ul_bitrate_67": -0.59076,
        "ul_total_bytes_non_incr_67": -0.57065,
        "dl_total_bytes_non_incr_67": -0.68178,
        "dl_bitrate_68": -0.70023,
        "ul_bitrate_68": -0.57627,
        "ul_total_bytes_non_incr_68": -0.55724,
        "dl_total_bytes_non_incr_68": -0.67683,
        "dl_bitrate_69": -0.05101,
        "ul_bitrate_69": 0.27101,
        "ul_total_bytes_non_incr_69": 0.30837,
        "dl_total_bytes_non_incr_69": -0.0167,
        "dl_bitrate_70": -0.71035,
        "ul_bitrate_70": 0.53924,
        "ul_total_bytes_non_incr_70": 0.58929,
        "dl_total_bytes_non_incr_70": -0.69456,
        "dl_bitrate_71": -0.71771,
        "ul_bitrate_71": 0.58447,
        "ul_total_bytes_non_incr_71": 0.5955,
        "dl_total_bytes_non_incr_71": -0.67641,
        "dl_bitrate_72": -0.76443,
        "ul_bitrate_72": 0.3159,
        "ul_total_bytes_non_incr_72": 0.39396,
        "dl_total_bytes_non_incr_72": -0.73629,
        "dl_bitrate_73": -0.32745,
        "ul_bitrate_73": -0.57514,
        "ul_total_bytes_non_incr_73": -0.55783,
        "dl_total_bytes_non_incr_73": -0.30335,
        "dl_bitrate_74": -0.69742,
        "ul_bitrate_74": -0.58192,
        "ul_total_bytes_non_incr_74": -0.56328,
        "dl_total_bytes_non_incr_74": -0.66655,
        "dl_bitrate_75": -0.0902,
        "ul_bitrate_75": 0.05235,
        "ul_total_bytes_non_incr_75": 0.10767,
        "dl_total_bytes_non_incr_75": -0.06228,
        "dl_bitrate_76": -0.7782,
        "ul_bitrate_76": 0.30565,
        "ul_total_bytes_non_incr_76": 0.35593,
        "dl_total_bytes_non_incr_76": -0.75066,
        "dl_bitrate_77": -0.73508,
        "ul_bitrate_77": 0.46134,
        "ul_total_bytes_non_incr_77": -0.70374,
        "dl_total_bytes_non_incr_77": -1.11436,
        "dl_bitrate_78": -0.72324,
        "ul_bitrate_78": 0.4595,
        "ul_total_bytes_non_incr_78": 0.52212,
        "dl_total_bytes_non_incr_78": -0.69146,
        "dl_bitrate_79": -0.37004,
        "ul_bitrate_79": -0.25373,
        "ul_total_bytes_non_incr_79": -0.21866,
        "dl_total_bytes_non_incr_79": -0.34576,
        "dl_bitrate_80": -0.70538,
        "ul_bitrate_80": -0.57903,
        "ul_total_bytes_non_incr_80": -0.56024,
        "dl_total_bytes_non_incr_80": -0.66524,
        "dl_bitrate_81": -0.03139,
        "ul_bitrate_81": -0.33173,
        "ul_total_bytes_non_incr_81": -0.31341,
        "dl_total_bytes_non_incr_81": -0.00525,
        "dl_bitrate_82": -0.78156,
        "ul_bitrate_82": 0.33823,
        "ul_total_bytes_non_incr_82": 0.42782,
        "dl_total_bytes_non_incr_82": -0.75187,
        "dl_bitrate_83": -0.73991,
        "ul_bitrate_83": 0.38598,
        "ul_total_bytes_non_incr_83": 0.44106,
        "dl_total_bytes_non_incr_83": -0.70753,
        "dl_bitrate_84": -0.73577,
        "ul_bitrate_84": 0.47774,
        "ul_total_bytes_non_incr_84": 0.53413,
        "dl_total_bytes_non_incr_84": -0.70389,
        "dl_bitrate_85": -0.41095,
        "ul_bitrate_85": 0.1309,
        "ul_total_bytes_non_incr_85": 0.19396,
        "dl_total_bytes_non_incr_85": -0.39205,
        "dl_bitrate_86": -0.6984,
        "ul_bitrate_86": -0.58072,
        "ul_total_bytes_non_incr_86": -0.56298,
        "dl_total_bytes_non_incr_86": -0.66908,
        "dl_bitrate_87": -0.56914,
        "ul_bitrate_87": -0.56817,
        "ul_total_bytes_non_incr_87": -0.55417,
        "dl_total_bytes_non_incr_87": -0.5752,
        "dl_bitrate_88": -0.19841,
        "ul_bitrate_88": 0.21273,
        "ul_total_bytes_non_incr_88": -0.7176,
        "dl_total_bytes_non_incr_88": -1.10758,
        "dl_bitrate_89": -0.73374,
        "ul_bitrate_89": 0.4252,
        "ul_total_bytes_non_incr_89": 0.47801,
        "dl_total_bytes_non_incr_89": -0.70475,
        "dl_bitrate_90": -0.64427,
        "ul_bitrate_90": 0.76146,
        "ul_total_bytes_non_incr_90": 0.74761,
        "dl_total_bytes_non_incr_90": -0.6178,
        "dl_bitrate_91": -0.37342,
        "ul_bitrate_91": 0.30178,
        "ul_total_bytes_non_incr_91": 0.38776,
        "dl_total_bytes_non_incr_91": -0.34378,
        "dl_bitrate_92": -0.71111,
        "ul_bitrate_92": -0.57588,
        "ul_total_bytes_non_incr_92": -0.56118,
        "dl_total_bytes_non_incr_92": -0.67426,
        "dl_bitrate_93": -0.63348,
        "ul_bitrate_93": -0.57233,
        "ul_total_bytes_non_incr_93": -0.55722,
        "dl_total_bytes_non_incr_93": -0.62527,
        "dl_bitrate_94": -0.16265,
        "ul_bitrate_94": 0.17344,
        "ul_total_bytes_non_incr_94": 0.24668,
        "dl_total_bytes_non_incr_94": -0.11006,
        "dl_bitrate_95": -0.71621,
        "ul_bitrate_95": 0.42012,
        "ul_total_bytes_non_incr_95": 0.48605,
        "dl_total_bytes_non_incr_95": -0.68978,
        "dl_bitrate_96": -0.70903,
        "ul_bitrate_96": 0.47604,
        "ul_total_bytes_non_incr_96": 0.51049,
        "dl_total_bytes_non_incr_96": -0.67484,
        "dl_bitrate_97": -0.76769,
        "ul_bitrate_97": 0.37801,
        "ul_total_bytes_non_incr_97": 0.45385,
        "dl_total_bytes_non_incr_97": -0.75037,
        "dl_bitrate_98": -0.40492,
        "ul_bitrate_98": -0.48142,
        "ul_total_bytes_non_incr_98": -0.44766,
        "dl_total_bytes_non_incr_98": -0.36992,
        "dl_bitrate_99": -0.69574,
        "ul_bitrate_99": -0.57659,
        "ul_total_bytes_non_incr_99": -0.55829,
        "dl_total_bytes_non_incr_99": -0.65667,
        "dl_bitrate_100": -0.02381,
        "ul_bitrate_100": -0.05073,
        "ul_total_bytes_non_incr_100": -0.05704,
        "dl_total_bytes_non_incr_100": 0.00684,
        "dl_bitrate_101": -0.67307,
        "ul_bitrate_101": 0.70343,
        "ul_total_bytes_non_incr_101": 0.74481,
        "dl_total_bytes_non_incr_101": -0.63929,
        "dl_bitrate_102": -0.6539,
        "ul_bitrate_102": 0.61752,
        "ul_total_bytes_non_incr_102": 0.61508,
        "dl_total_bytes_non_incr_102": -0.62246,
        "dl_bitrate_103": -0.77802,
        "ul_bitrate_103": 0.37097,
        "ul_total_bytes_non_incr_103": 0.45582,
        "dl_total_bytes_non_incr_103": -0.74692,
        "dl_bitrate_104": -0.36669,
        "ul_bitrate_104": -0.4555,
        "ul_total_bytes_non_incr_104": -0.42732,
        "dl_total_bytes_non_incr_104": -0.34225,
        "dl_bitrate_105": -0.69713,
        "ul_bitrate_105": -0.57097,
        "ul_total_bytes_non_incr_105": -0.55372,
        "dl_total_bytes_non_incr_105": -0.66082,
        "dl_bitrate_106": -0.08548,
        "ul_bitrate_106": -0.18821,
        "ul_total_bytes_non_incr_106": -0.15372,
        "dl_total_bytes_non_incr_106": -0.06363,
        "dl_bitrate_107": -0.73153,
        "ul_bitrate_107": 0.45997,
        "ul_total_bytes_non_incr_107": 0.50838,
        "dl_total_bytes_non_incr_107": -0.70329,
        "dl_bitrate_108": -0.71321,
        "ul_bitrate_108": 0.4281,
        "ul_total_bytes_non_incr_108": 0.49017,
        "dl_total_bytes_non_incr_108": -0.68819,
        "dl_bitrate_109": -0.73876,
        "ul_bitrate_109": 0.42683,
        "ul_total_bytes_non_incr_109": 0.47402,
        "dl_total_bytes_non_incr_109": -0.71296,
        "dl_bitrate_110": -0.39659,
        "ul_bitrate_110": -0.14783,
        "ul_total_bytes_non_incr_110": -0.10513,
        "dl_total_bytes_non_incr_110": -0.35562,
        "dl_bitrate_111": -0.69844,
        "ul_bitrate_111": -0.57154,
        "ul_total_bytes_non_incr_111": -0.55462,
        "dl_total_bytes_non_incr_111": -0.6761,
        "dl_bitrate_112": -0.0525,
        "ul_bitrate_112": -0.46135,
        "ul_total_bytes_non_incr_112": -0.43597,
        "dl_total_bytes_non_incr_112": -0.0191,
        "dl_bitrate_113": -0.69734,
        "ul_bitrate_113": 0.47564,
        "ul_total_bytes_non_incr_113": 0.48773,
        "dl_total_bytes_non_incr_113": -0.66667,
        "dl_bitrate_114": -0.73286,
        "ul_bitrate_114": 0.47321,
        "ul_total_bytes_non_incr_114": 0.55159,
        "dl_total_bytes_non_incr_114": -0.70042,
        "dl_bitrate_115": -0.73338,
        "ul_bitrate_115": 0.3406,
        "ul_total_bytes_non_incr_115": 0.40783,
        "dl_total_bytes_non_incr_115": -0.716,
        "dl_bitrate_116": -0.42807,
        "ul_bitrate_116": 0.17712,
        "ul_total_bytes_non_incr_116": 0.2381,
        "dl_total_bytes_non_incr_116": -0.47052,
        "dl_bitrate_117": -0.71286,
        "ul_bitrate_117": -0.57523,
        "ul_total_bytes_non_incr_117": -0.71228,
        "dl_total_bytes_non_incr_117": -1.11415,
        "dl_bitrate_118": -0.69982,
        "ul_bitrate_118": -0.57443,
        "ul_total_bytes_non_incr_118": -0.55551,
        "dl_total_bytes_non_incr_118": -0.66495,
        "dl_bitrate_119": -0.08123,
        "ul_bitrate_119": 0.16995,
        "ul_total_bytes_non_incr_119": 0.20424,
        "dl_total_bytes_non_incr_119": -0.05587,
        "dl_bitrate_120": -0.68818,
        "ul_bitrate_120": 0.63689,
        "ul_total_bytes_non_incr_120": 0.63949,
        "dl_total_bytes_non_incr_120": -0.65973,
        "hour": -0.90837,
        "dayofweek": 0.42338,
        "day": 0.42338
    }
}